pray/__init__.py
pray/core.py
pray/icond.py
pray-0.1.1.dist-info/LICENSE
pray-0.1.1.dist-info/METADATA
pray-0.1.1.dist-info/WHEEL
pray-0.1.1.dist-info/top_level.txt
pray-0.1.1.dist-info/RECORD
