Metadata-Version: 2.1
Name: pray
Version: 0.1.1
Summary: General relativistic ray tracing in python based on JAX
Home-page: https://github.com/adxsrc/pray
Author: Chi-kwan Chan
Author-email: chanc@arizona.edu
License: UNKNOWN
Platform: UNKNOWN
Requires-Python: >=3.7
License-File: LICENSE
Requires-Dist: fadge (==0.1.1)
